kmaps/__init__.py
kmaps/folmaps.py
kmaps/kmaps.py
kmaps-0.0.14.dist-info/LICENSE
kmaps-0.0.14.dist-info/METADATA
kmaps-0.0.14.dist-info/WHEEL
kmaps-0.0.14.dist-info/dependency_links.txt
kmaps-0.0.14.dist-info/top_level.txt
kmaps-0.0.14.dist-info/RECORD
