Metadata-Version: 2.1
Name: kmaps
Version: 0.0.14
Summary: TBA
Home-page: https://github.com/ChangwhaOh/kmaps
Author: Changwha Oh
Author-email: coh4@vols.utk.edu
License: MIT license
Keywords: kmaps
Classifier: Development Status :: 2 - Pre-Alpha
Classifier: Intended Audience :: Developers
Classifier: License :: OSI Approved :: MIT License
Classifier: Natural Language :: English
Classifier: Programming Language :: Python :: 3
Classifier: Programming Language :: Python :: 3.7
Classifier: Programming Language :: Python :: 3.8
Classifier: Programming Language :: Python :: 3.9
Classifier: Programming Language :: Python :: 3.10
Requires-Python: >=3.7
License-File: LICENSE
Requires-Dist: folium
Requires-Dist: ipyleaflet
Requires-Dist: ipywidgets
Requires-Dist: ipyfilechooser
Requires-Dist: geopandas
Requires-Dist: spopt
Requires-Dist: httpx
